bakalapi/__init__.py
bakalapi/client.py
bakalapi/models.py
bakalapi-1.0.0.dist-info/METADATA
bakalapi-1.0.0.dist-info/WHEEL
bakalapi-1.0.0.dist-info/top_level.txt
bakalapi-1.0.0.dist-info/RECORD
