Metadata-Version: 2.4
Name: bakalapi
Version: 1.0.0
Summary: A Python library for accessing the Bakalapi timetable API
Author-email: Your Name <your.email@example.com>
License: MIT
Project-URL: Homepage, https://github.com/yourusername/bakalapi-libs
Project-URL: Repository, https://github.com/yourusername/bakalapi-libs
Project-URL: Issues, https://github.com/yourusername/bakalapi-libs/issues
Keywords: bakalapi,timetable,api,school
Classifier: Development Status :: 4 - Beta
Classifier: Intended Audience :: Developers
Classifier: License :: OSI Approved :: MIT License
Classifier: Programming Language :: Python :: 3
Classifier: Programming Language :: Python :: 3.7
Classifier: Programming Language :: Python :: 3.8
Classifier: Programming Language :: Python :: 3.9
Classifier: Programming Language :: Python :: 3.10
Classifier: Programming Language :: Python :: 3.11
Classifier: Programming Language :: Python :: 3.12
Requires-Python: >=3.7
Requires-Dist: requests>=2.31.0
